qwixtractor/__init__.py
qwixtractor/qwixtractor.py
qwixtractor-0.1.0.dist-info/LICENSE
qwixtractor-0.1.0.dist-info/WHEEL
qwixtractor-0.1.0.dist-info/METADATA
qwixtractor-0.1.0.dist-info/RECORD
