Metadata-Version: 2.1
Name: qwixtractor
Version: 0.1.0
Summary: Extract data from the Quarterly Workforce Indicators
License: MIT
Author: Rodrigo Franco
Requires-Python: >=3.9
Classifier: License :: OSI Approved :: MIT License
Classifier: Programming Language :: Python :: 3
Classifier: Programming Language :: Python :: 3.10
Classifier: Programming Language :: Python :: 3.9
Requires-Dist: pandas (>=1.4.3)
Requires-Dist: progressbar2 (>=4.0.0)
Requires-Dist: requests (>=2.28.1)
